{
    "speed": "16.000",
    "name": "97",
    "time": "92",
    "points": [
        {
            "lat": -17.8111,
            "lng": -63.0889
        },
        {
            "lat": -17.81115,
            "lng": -63.08945
        },
        {
            "lat": -17.811183,
            "lng": -63.08995
        },
        {
            "lat": -17.811217,
            "lng": -63.0905
        },
        {
            "lat": -17.811283,
            "lng": -63.09105
        },
        {
            "lat": -17.811317,
            "lng": -63.091583
        },
        {
            "lat": -17.811367,
            "lng": -63.0921
        },
        {
            "lat": -17.811417,
            "lng": -63.092633
        },
        {
            "lat": -17.81145,
            "lng": -63.093167
        },
        {
            "lat": -17.8115,
            "lng": -63.093667
        },
        {
            "lat": -17.81155,
            "lng": -63.09415
        },
        {
            "lat": -17.811567,
            "lng": -63.09465
        },
        {
            "lat": -17.811617,
            "lng": -63.095183
        },
        {
            "lat": -17.81165,
            "lng": -63.095683
        },
        {
            "lat": -17.8117,
            "lng": -63.096183
        },
        {
            "lat": -17.811767,
            "lng": -63.0967
        },
        {
            "lat": -17.811817,
            "lng": -63.0972
        },
        {
            "lat": -17.81155,
            "lng": -63.09755
        },
        {
            "lat": -17.811083,
            "lng": -63.097617
        },
        {
            "lat": -17.8106,
            "lng": -63.097683
        },
        {
            "lat": -17.810117,
            "lng": -63.097733
        },
        {
            "lat": -17.810033,
            "lng": -63.098167
        },
        {
            "lat": -17.810117,
            "lng": -63.098667
        },
        {
            "lat": -17.8103,
            "lng": -63.099117
        },
        {
            "lat": -17.810567,
            "lng": -63.099517
        },
        {
            "lat": -17.8108,
            "lng": -63.099983
        },
        {
            "lat": -17.811017,
            "lng": -63.100433
        },
        {
            "lat": -17.81125,
            "lng": -63.10085
        },
        {
            "lat": -17.811467,
            "lng": -63.1013
        },
        {
            "lat": -17.8117,
            "lng": -63.101783
        },
        {
            "lat": -17.81195,
            "lng": -63.10225
        },
        {
            "lat": -17.812167,
            "lng": -63.1027
        },
        {
            "lat": -17.8124,
            "lng": -63.103133
        },
        {
            "lat": -17.812617,
            "lng": -63.103583
        },
        {
            "lat": -17.81285,
            "lng": -63.104083
        },
        {
            "lat": -17.8131,
            "lng": -63.10455
        },
        {
            "lat": -17.813333,
            "lng": -63.105017
        },
        {
            "lat": -17.813567,
            "lng": -63.105467
        },
        {
            "lat": -17.8138,
            "lng": -63.105933
        },
        {
            "lat": -17.814033,
            "lng": -63.106383
        },
        {
            "lat": -17.814283,
            "lng": -63.10685
        },
        {
            "lat": -17.8145,
            "lng": -63.107317
        },
        {
            "lat": -17.814767,
            "lng": -63.107783
        },
        {
            "lat": -17.815,
            "lng": -63.108217
        },
        {
            "lat": -17.8152,
            "lng": -63.108667
        },
        {
            "lat": -17.815433,
            "lng": -63.10915
        },
        {
            "lat": -17.815683,
            "lng": -63.109617
        },
        {
            "lat": -17.816017,
            "lng": -63.10995
        },
        {
            "lat": -17.816517,
            "lng": -63.109967
        },
        {
            "lat": -17.816967,
            "lng": -63.109983
        },
        {
            "lat": -17.8175,
            "lng": -63.109983
        },
        {
            "lat": -17.81795,
            "lng": -63.110017
        },
        {
            "lat": -17.817917,
            "lng": -63.11045
        },
        {
            "lat": -17.817717,
            "lng": -63.110917
        },
        {
            "lat": -17.817533,
            "lng": -63.1114
        },
        {
            "lat": -17.81735,
            "lng": -63.11185
        },
        {
            "lat": -17.817133,
            "lng": -63.11235
        },
        {
            "lat": -17.816933,
            "lng": -63.1128
        },
        {
            "lat": -17.81675,
            "lng": -63.113267
        },
        {
            "lat": -17.81655,
            "lng": -63.113733
        },
        {
            "lat": -17.816383,
            "lng": -63.1142
        },
        {
            "lat": -17.816183,
            "lng": -63.114633
        },
        {
            "lat": -17.816417,
            "lng": -63.115117
        },
        {
            "lat": -17.816667,
            "lng": -63.115583
        },
        {
            "lat": -17.816883,
            "lng": -63.116
        },
        {
            "lat": -17.817117,
            "lng": -63.11645
        },
        {
            "lat": -17.817333,
            "lng": -63.1169
        },
        {
            "lat": -17.817567,
            "lng": -63.117367
        },
        {
            "lat": -17.817783,
            "lng": -63.117817
        },
        {
            "lat": -17.818017,
            "lng": -63.118283
        },
        {
            "lat": -17.818267,
            "lng": -63.118717
        },
        {
            "lat": -17.818483,
            "lng": -63.119167
        },
        {
            "lat": -17.818717,
            "lng": -63.119583
        },
        {
            "lat": -17.818967,
            "lng": -63.12005
        },
        {
            "lat": -17.81915,
            "lng": -63.120467
        },
        {
            "lat": -17.8194,
            "lng": -63.12095
        },
        {
            "lat": -17.819633,
            "lng": -63.121383
        },
        {
            "lat": -17.819867,
            "lng": -63.121833
        },
        {
            "lat": -17.8201,
            "lng": -63.1223
        },
        {
            "lat": -17.820367,
            "lng": -63.122783
        },
        {
            "lat": -17.8206,
            "lng": -63.123283
        },
        {
            "lat": -17.82085,
            "lng": -63.123783
        },
        {
            "lat": -17.8211,
            "lng": -63.12425
        },
        {
            "lat": -17.82135,
            "lng": -63.124717
        },
        {
            "lat": -17.82155,
            "lng": -63.12515
        },
        {
            "lat": -17.821767,
            "lng": -63.125567
        },
        {
            "lat": -17.822,
            "lng": -63.126033
        },
        {
            "lat": -17.82225,
            "lng": -63.1265
        },
        {
            "lat": -17.822467,
            "lng": -63.12695
        },
        {
            "lat": -17.822683,
            "lng": -63.127367
        },
        {
            "lat": -17.822917,
            "lng": -63.127817
        },
        {
            "lat": -17.823167,
            "lng": -63.128283
        },
        {
            "lat": -17.823417,
            "lng": -63.128783
        },
        {
            "lat": -17.82365,
            "lng": -63.129267
        },
        {
            "lat": -17.8239,
            "lng": -63.12975
        },
        {
            "lat": -17.824117,
            "lng": -63.130167
        },
        {
            "lat": -17.824383,
            "lng": -63.13065
        },
        {
            "lat": -17.824583,
            "lng": -63.131083
        },
        {
            "lat": -17.8248,
            "lng": -63.1315
        },
        {
            "lat": -17.82475,
            "lng": -63.131983
        },
        {
            "lat": -17.824417,
            "lng": -63.1323
        },
        {
            "lat": -17.824083,
            "lng": -63.13265
        },
        {
            "lat": -17.823733,
            "lng": -63.13305
        },
        {
            "lat": -17.823367,
            "lng": -63.133417
        },
        {
            "lat": -17.823033,
            "lng": -63.133783
        },
        {
            "lat": -17.822717,
            "lng": -63.13415
        },
        {
            "lat": -17.822383,
            "lng": -63.1345
        },
        {
            "lat": -17.822033,
            "lng": -63.13485
        },
        {
            "lat": -17.821683,
            "lng": -63.135183
        },
        {
            "lat": -17.8213,
            "lng": -63.135583
        },
        {
            "lat": -17.82095,
            "lng": -63.135967
        },
        {
            "lat": -17.820583,
            "lng": -63.13635
        },
        {
            "lat": -17.82025,
            "lng": -63.1367
        },
        {
            "lat": -17.8199,
            "lng": -63.1371
        },
        {
            "lat": -17.819567,
            "lng": -63.137467
        },
        {
            "lat": -17.819233,
            "lng": -63.137833
        },
        {
            "lat": -17.81885,
            "lng": -63.138217
        },
        {
            "lat": -17.81845,
            "lng": -63.13865
        },
        {
            "lat": -17.8181,
            "lng": -63.139017
        },
        {
            "lat": -17.817767,
            "lng": -63.139383
        },
        {
            "lat": -17.817467,
            "lng": -63.139733
        },
        {
            "lat": -17.817083,
            "lng": -63.13985
        },
        {
            "lat": -17.816767,
            "lng": -63.139483
        },
        {
            "lat": -17.816417,
            "lng": -63.1391
        },
        {
            "lat": -17.8161,
            "lng": -63.13875
        },
        {
            "lat": -17.815767,
            "lng": -63.1384
        },
        {
            "lat": -17.815417,
            "lng": -63.138017
        },
        {
            "lat": -17.815067,
            "lng": -63.137667
        },
        {
            "lat": -17.814683,
            "lng": -63.137367
        },
        {
            "lat": -17.81425,
            "lng": -63.137133
        },
        {
            "lat": -17.813767,
            "lng": -63.136967
        },
        {
            "lat": -17.813267,
            "lng": -63.136867
        },
        {
            "lat": -17.8128,
            "lng": -63.13685
        },
        {
            "lat": -17.812383,
            "lng": -63.136733
        },
        {
            "lat": -17.812083,
            "lng": -63.136383
        },
        {
            "lat": -17.81185,
            "lng": -63.136733
        },
        {
            "lat": -17.811817,
            "lng": -63.137267
        },
        {
            "lat": -17.811783,
            "lng": -63.137767
        },
        {
            "lat": -17.81175,
            "lng": -63.138283
        },
        {
            "lat": -17.811733,
            "lng": -63.138817
        },
        {
            "lat": -17.8117,
            "lng": -63.139317
        },
        {
            "lat": -17.811667,
            "lng": -63.13985
        },
        {
            "lat": -17.811633,
            "lng": -63.140367
        },
        {
            "lat": -17.811617,
            "lng": -63.140867
        },
        {
            "lat": -17.811583,
            "lng": -63.141367
        },
        {
            "lat": -17.811567,
            "lng": -63.14185
        },
        {
            "lat": -17.811533,
            "lng": -63.142333
        },
        {
            "lat": -17.81145,
            "lng": -63.142867
        },
        {
            "lat": -17.81125,
            "lng": -63.1433
        },
        {
            "lat": -17.811433,
            "lng": -63.14375
        },
        {
            "lat": -17.811433,
            "lng": -63.144267
        },
        {
            "lat": -17.811383,
            "lng": -63.14475
        },
        {
            "lat": -17.811317,
            "lng": -63.145267
        },
        {
            "lat": -17.81125,
            "lng": -63.145833
        },
        {
            "lat": -17.8112,
            "lng": -63.146317
        },
        {
            "lat": -17.811133,
            "lng": -63.146883
        },
        {
            "lat": -17.811067,
            "lng": -63.1474
        },
        {
            "lat": -17.810917,
            "lng": -63.14785
        },
        {
            "lat": -17.8107,
            "lng": -63.148267
        },
        {
            "lat": -17.8104,
            "lng": -63.148717
        },
        {
            "lat": -17.81005,
            "lng": -63.148917
        },
        {
            "lat": -17.8096,
            "lng": -63.148583
        },
        {
            "lat": -17.809167,
            "lng": -63.148283
        },
        {
            "lat": -17.808733,
            "lng": -63.148
        },
        {
            "lat": -17.8083,
            "lng": -63.1477
        },
        {
            "lat": -17.807883,
            "lng": -63.147383
        },
        {
            "lat": -17.807467,
            "lng": -63.147117
        },
        {
            "lat": -17.80705,
            "lng": -63.146817
        },
        {
            "lat": -17.806667,
            "lng": -63.146533
        },
        {
            "lat": -17.8062,
            "lng": -63.14625
        },
        {
            "lat": -17.8058,
            "lng": -63.14595
        },
        {
            "lat": -17.8053,
            "lng": -63.145917
        },
        {
            "lat": -17.804817,
            "lng": -63.145917
        },
        {
            "lat": -17.80435,
            "lng": -63.145783
        },
        {
            "lat": -17.803883,
            "lng": -63.145633
        },
        {
            "lat": -17.803417,
            "lng": -63.1455
        },
        {
            "lat": -17.8029,
            "lng": -63.145333
        },
        {
            "lat": -17.80245,
            "lng": -63.1452
        },
        {
            "lat": -17.801967,
            "lng": -63.14505
        },
        {
            "lat": -17.801517,
            "lng": -63.144933
        },
        {
            "lat": -17.801017,
            "lng": -63.144783
        },
        {
            "lat": -17.8005,
            "lng": -63.144617
        },
        {
            "lat": -17.8,
            "lng": -63.144467
        },
        {
            "lat": -17.799717,
            "lng": -63.144783
        },
        {
            "lat": -17.799583,
            "lng": -63.1453
        },
        {
            "lat": -17.79945,
            "lng": -63.1458
        },
        {
            "lat": -17.799317,
            "lng": -63.1463
        },
        {
            "lat": -17.799217,
            "lng": -63.14675
        },
        {
            "lat": -17.799083,
            "lng": -63.14725
        },
        {
            "lat": -17.798967,
            "lng": -63.147733
        },
        {
            "lat": -17.798833,
            "lng": -63.14825
        },
        {
            "lat": -17.7987,
            "lng": -63.148767
        },
        {
            "lat": -17.798567,
            "lng": -63.149217
        },
        {
            "lat": -17.798233,
            "lng": -63.149567
        },
        {
            "lat": -17.797717,
            "lng": -63.149567
        },
        {
            "lat": -17.79725,
            "lng": -63.149417
        },
        {
            "lat": -17.796717,
            "lng": -63.149283
        },
        {
            "lat": -17.796267,
            "lng": -63.14915
        },
        {
            "lat": -17.795817,
            "lng": -63.149033
        },
        {
            "lat": -17.7954,
            "lng": -63.148883
        },
        {
            "lat": -17.794917,
            "lng": -63.1488
        },
        {
            "lat": -17.794483,
            "lng": -63.1487
        },
        {
            "lat": -17.794,
            "lng": -63.1486
        },
        {
            "lat": -17.793533,
            "lng": -63.148467
        },
        {
            "lat": -17.793,
            "lng": -63.148367
        },
        {
            "lat": -17.7925,
            "lng": -63.1483
        },
        {
            "lat": -17.792,
            "lng": -63.14825
        },
        {
            "lat": -17.79155,
            "lng": -63.148217
        },
        {
            "lat": -17.7911,
            "lng": -63.148183
        },
        {
            "lat": -17.790633,
            "lng": -63.1482
        },
        {
            "lat": -17.789883,
            "lng": -63.147967
        },
        {
            "lat": -17.789167,
            "lng": -63.1481
        },
        {
            "lat": -17.789033,
            "lng": -63.148367
        },
        {
            "lat": -17.789317,
            "lng": -63.148867
        },
        {
            "lat": -17.789517,
            "lng": -63.14935
        },
        {
            "lat": -17.789683,
            "lng": -63.149833
        },
        {
            "lat": -17.78985,
            "lng": -63.150333
        },
        {
            "lat": -17.790067,
            "lng": -63.15085
        },
        {
            "lat": -17.790283,
            "lng": -63.1514
        },
        {
            "lat": -17.79045,
            "lng": -63.151833
        },
        {
            "lat": -17.790583,
            "lng": -63.152367
        },
        {
            "lat": -17.79075,
            "lng": -63.15285
        },
        {
            "lat": -17.790933,
            "lng": -63.153333
        },
        {
            "lat": -17.7911,
            "lng": -63.1538
        },
        {
            "lat": -17.791283,
            "lng": -63.154267
        },
        {
            "lat": -17.791467,
            "lng": -63.154767
        },
        {
            "lat": -17.79165,
            "lng": -63.1553
        },
        {
            "lat": -17.791833,
            "lng": -63.155767
        },
        {
            "lat": -17.792267,
            "lng": -63.155867
        },
        {
            "lat": -17.792733,
            "lng": -63.1558
        },
        {
            "lat": -17.793133,
            "lng": -63.156083
        },
        {
            "lat": -17.793567,
            "lng": -63.156317
        },
        {
            "lat": -17.794,
            "lng": -63.1565
        },
        {
            "lat": -17.79445,
            "lng": -63.1567
        },
        {
            "lat": -17.794883,
            "lng": -63.1569
        },
        {
            "lat": -17.7953,
            "lng": -63.15715
        },
        {
            "lat": -17.7952,
            "lng": -63.157667
        },
        {
            "lat": -17.795,
            "lng": -63.158183
        },
        {
            "lat": -17.794867,
            "lng": -63.158683
        },
        {
            "lat": -17.794767,
            "lng": -63.159267
        },
        {
            "lat": -17.794683,
            "lng": -63.15975
        },
        {
            "lat": -17.794617,
            "lng": -63.1603
        },
        {
            "lat": -17.79455,
            "lng": -63.1608
        },
        {
            "lat": -17.794517,
            "lng": -63.1613
        },
        {
            "lat": -17.794433,
            "lng": -63.161767
        },
        {
            "lat": -17.794133,
            "lng": -63.162183
        },
        {
            "lat": -17.79365,
            "lng": -63.16245
        },
        {
            "lat": -17.793167,
            "lng": -63.162617
        },
        {
            "lat": -17.7927,
            "lng": -63.162733
        },
        {
            "lat": -17.792467,
            "lng": -63.163133
        },
        {
            "lat": -17.7924,
            "lng": -63.16365
        },
        {
            "lat": -17.792217,
            "lng": -63.164167
        },
        {
            "lat": -17.791983,
            "lng": -63.164683
        },
        {
            "lat": -17.791667,
            "lng": -63.16495
        },
        {
            "lat": -17.791233,
            "lng": -63.164817
        },
        {
            "lat": -17.79075,
            "lng": -63.16465
        },
        {
            "lat": -17.7903,
            "lng": -63.1645
        },
        {
            "lat": -17.789867,
            "lng": -63.164333
        },
        {
            "lat": -17.789417,
            "lng": -63.164183
        },
        {
            "lat": -17.788917,
            "lng": -63.164017
        },
        {
            "lat": -17.78845,
            "lng": -63.163867
        },
        {
            "lat": -17.78795,
            "lng": -63.1637
        },
        {
            "lat": -17.78785,
            "lng": -63.163267
        },
        {
            "lat": -17.788033,
            "lng": -63.1628
        },
        {
            "lat": -17.788267,
            "lng": -63.162367
        },
        {
            "lat": -17.7879,
            "lng": -63.16225
        },
        {
            "lat": -17.7876,
            "lng": -63.162717
        },
        {
            "lat": -17.787633,
            "lng": -63.163283
        },
        {
            "lat": -17.787567,
            "lng": -63.163767
        },
        {
            "lat": -17.787317,
            "lng": -63.164183
        },
        {
            "lat": -17.787067,
            "lng": -63.164667
        },
        {
            "lat": -17.78685,
            "lng": -63.165133
        },
        {
            "lat": -17.786733,
            "lng": -63.165633
        },
        {
            "lat": -17.786633,
            "lng": -63.166233
        },
        {
            "lat": -17.7865,
            "lng": -63.16675
        },
        {
            "lat": -17.786333,
            "lng": -63.167317
        },
        {
            "lat": -17.786133,
            "lng": -63.16785
        },
        {
            "lat": -17.78595,
            "lng": -63.1683
        },
        {
            "lat": -17.785717,
            "lng": -63.16875
        },
        {
            "lat": -17.785467,
            "lng": -63.1692
        },
        {
            "lat": -17.7852,
            "lng": -63.169617
        },
        {
            "lat": -17.784983,
            "lng": -63.170117
        },
        {
            "lat": -17.784917,
            "lng": -63.170667
        },
        {
            "lat": -17.784533,
            "lng": -63.170933
        },
        {
            "lat": -17.784033,
            "lng": -63.171017
        },
        {
            "lat": -17.784017,
            "lng": -63.1715
        },
        {
            "lat": -17.784033,
            "lng": -63.17205
        },
        {
            "lat": -17.784083,
            "lng": -63.172667
        },
        {
            "lat": -17.784117,
            "lng": -63.1732
        },
        {
            "lat": -17.784183,
            "lng": -63.173717
        },
        {
            "lat": -17.784217,
            "lng": -63.174233
        },
        {
            "lat": -17.784267,
            "lng": -63.17475
        },
        {
            "lat": -17.7843,
            "lng": -63.175283
        },
        {
            "lat": -17.78435,
            "lng": -63.1758
        },
        {
            "lat": -17.784767,
            "lng": -63.175867
        },
        {
            "lat": -17.785267,
            "lng": -63.17575
        },
        {
            "lat": -17.785733,
            "lng": -63.175733
        },
        {
            "lat": -17.7858,
            "lng": -63.1762
        },
        {
            "lat": -17.785917,
            "lng": -63.176717
        },
        {
            "lat": -17.786083,
            "lng": -63.177267
        },
        {
            "lat": -17.7862,
            "lng": -63.177767
        },
        {
            "lat": -17.786333,
            "lng": -63.17825
        },
        {
            "lat": -17.78645,
            "lng": -63.1787
        },
        {
            "lat": -17.786567,
            "lng": -63.1792
        },
        {
            "lat": -17.786817,
            "lng": -63.17965
        },
        {
            "lat": -17.78705,
            "lng": -63.180067
        },
        {
            "lat": -17.787033,
            "lng": -63.18055
        },
        {
            "lat": -17.7869,
            "lng": -63.1812
        },
        {
            "lat": -17.786967,
            "lng": -63.181667
        },
        {
            "lat": -17.786983,
            "lng": -63.182167
        },
        {
            "lat": -17.7871,
            "lng": -63.182683
        },
        {
            "lat": -17.787267,
            "lng": -63.18315
        },
        {
            "lat": -17.787317,
            "lng": -63.183717
        },
        {
            "lat": -17.78735,
            "lng": -63.184233
        },
        {
            "lat": -17.787417,
            "lng": -63.18465
        },
        {
            "lat": -17.787533,
            "lng": -63.185267
        },
        {
            "lat": -17.787633,
            "lng": -63.185833
        },
        {
            "lat": -17.7878,
            "lng": -63.186383
        },
        {
            "lat": -17.787983,
            "lng": -63.1869
        },
        {
            "lat": -17.78825,
            "lng": -63.187417
        },
        {
            "lat": -17.788633,
            "lng": -63.187833
        },
        {
            "lat": -17.789067,
            "lng": -63.188217
        },
        {
            "lat": -17.789433,
            "lng": -63.1885
        },
        {
            "lat": -17.78985,
            "lng": -63.18875
        },
        {
            "lat": -17.790317,
            "lng": -63.1891
        },
        {
            "lat": -17.79075,
            "lng": -63.189417
        },
        {
            "lat": -17.79115,
            "lng": -63.189733
        },
        {
            "lat": -17.79155,
            "lng": -63.190083
        },
        {
            "lat": -17.791917,
            "lng": -63.190317
        },
        {
            "lat": -17.7923,
            "lng": -63.190617
        },
        {
            "lat": -17.7927,
            "lng": -63.190767
        },
        {
            "lat": -17.791917,
            "lng": -63.19155
        },
        {
            "lat": -17.79145,
            "lng": -63.19195
        },
        {
            "lat": -17.7909,
            "lng": -63.192183
        },
        {
            "lat": -17.790383,
            "lng": -63.192233
        },
        {
            "lat": -17.789933,
            "lng": -63.192183
        },
        {
            "lat": -17.789633,
            "lng": -63.192333
        },
        {
            "lat": -17.789783,
            "lng": -63.192833
        },
        {
            "lat": -17.789783,
            "lng": -63.19335
        },
        {
            "lat": -17.789917,
            "lng": -63.1937
        },
        {
            "lat": -17.789933,
            "lng": -63.19415
        },
        {
            "lat": -17.790017,
            "lng": -63.194667
        },
        {
            "lat": -17.790233,
            "lng": -63.195117
        },
        {
            "lat": -17.790433,
            "lng": -63.195567
        },
        {
            "lat": -17.790633,
            "lng": -63.196067
        },
        {
            "lat": -17.790817,
            "lng": -63.196517
        },
        {
            "lat": -17.79105,
            "lng": -63.197
        },
        {
            "lat": -17.791267,
            "lng": -63.197483
        },
        {
            "lat": -17.791517,
            "lng": -63.198033
        },
        {
            "lat": -17.791717,
            "lng": -63.198567
        },
        {
            "lat": -17.791917,
            "lng": -63.199033
        },
        {
            "lat": -17.792133,
            "lng": -63.199567
        },
        {
            "lat": -17.792333,
            "lng": -63.200017
        },
        {
            "lat": -17.792533,
            "lng": -63.2005
        },
        {
            "lat": -17.79275,
            "lng": -63.201
        },
        {
            "lat": -17.79275,
            "lng": -63.201
        },
        {
            "lat": -17.792967,
            "lng": -63.201517
        },
        {
            "lat": -17.7932,
            "lng": -63.202067
        },
        {
            "lat": -17.793433,
            "lng": -63.202567
        },
        {
            "lat": -17.793667,
            "lng": -63.2031
        },
        {
            "lat": -17.793867,
            "lng": -63.203567
        },
        {
            "lat": -17.794033,
            "lng": -63.203967
        },
        {
            "lat": -17.794133,
            "lng": -63.204167
        },
        {
            "lat": -17.79375,
            "lng": -63.204317
        },
        {
            "lat": -17.79335,
            "lng": -63.204433
        },
        {
            "lat": -17.79305,
            "lng": -63.204517
        },
        {
            "lat": -17.792583,
            "lng": -63.204617
        },
        {
            "lat": -17.792183,
            "lng": -63.204667
        },
        {
            "lat": -17.791733,
            "lng": -63.204717
        },
        {
            "lat": -17.791283,
            "lng": -63.20475
        },
        {
            "lat": -17.790817,
            "lng": -63.2048
        },
        {
            "lat": -17.7903,
            "lng": -63.204867
        },
        {
            "lat": -17.789833,
            "lng": -63.204933
        },
        {
            "lat": -17.78935,
            "lng": -63.204917
        },
        {
            "lat": -17.788883,
            "lng": -63.204883
        },
        {
            "lat": -17.78835,
            "lng": -63.20485
        },
        {
            "lat": -17.787817,
            "lng": -63.204833
        },
        {
            "lat": -17.787367,
            "lng": -63.2048
        },
        {
            "lat": -17.7868,
            "lng": -63.20475
        },
        {
            "lat": -17.7863,
            "lng": -63.204717
        },
        {
            "lat": -17.785767,
            "lng": -63.204667
        },
        {
            "lat": -17.7855,
            "lng": -63.20465
        },
        {
            "lat": -17.7854,
            "lng": -63.20445
        },
        {
            "lat": -17.7851,
            "lng": -63.204617
        },
        {
            "lat": -17.78495,
            "lng": -63.2046
        },
        {
            "lat": -17.784567,
            "lng": -63.204567
        },
        {
            "lat": -17.784567,
            "lng": -63.204483
        },
        {
            "lat": -17.784517,
            "lng": -63.204483
        },
        {
            "lat": -17.784033,
            "lng": -63.204517
        },
        {
            "lat": -17.783567,
            "lng": -63.20445
        },
        {
            "lat": -17.783067,
            "lng": -63.204383
        },
        {
            "lat": -17.782583,
            "lng": -63.204333
        },
        {
            "lat": -17.7821,
            "lng": -63.204267
        },
        {
            "lat": -17.781633,
            "lng": -63.2042
        },
        {
            "lat": -17.78115,
            "lng": -63.204133
        },
        {
            "lat": -17.78065,
            "lng": -63.204067
        },
        {
            "lat": -17.780183,
            "lng": -63.204
        },
        {
            "lat": -17.779733,
            "lng": -63.203917
        },
        {
            "lat": -17.7792,
            "lng": -63.203833
        },
        {
            "lat": -17.778717,
            "lng": -63.203767
        },
        {
            "lat": -17.778233,
            "lng": -63.2037
        },
        {
            "lat": -17.777817,
            "lng": -63.2035
        },
        {
            "lat": -17.777433,
            "lng": -63.203383
        },
        {
            "lat": -17.777367,
            "lng": -63.2038
        },
        {
            "lat": -17.777433,
            "lng": -63.204283
        },
        {
            "lat": -17.777417,
            "lng": -63.204767
        },
        {
            "lat": -17.777283,
            "lng": -63.205233
        },
        {
            "lat": -17.77745,
            "lng": -63.205717
        },
        {
            "lat": -17.77745,
            "lng": -63.206217
        },
        {
            "lat": -17.77745,
            "lng": -63.206733
        },
        {
            "lat": -17.77745,
            "lng": -63.207267
        },
        {
            "lat": -17.777467,
            "lng": -63.207733
        },
        {
            "lat": -17.777483,
            "lng": -63.208217
        },
        {
            "lat": -17.7775,
            "lng": -63.2087
        },
        {
            "lat": -17.777517,
            "lng": -63.209183
        },
        {
            "lat": -17.777517,
            "lng": -63.209667
        },
        {
            "lat": -17.777533,
            "lng": -63.21015
        },
        {
            "lat": -17.77755,
            "lng": -63.210683
        },
        {
            "lat": -17.777567,
            "lng": -63.211217
        },
        {
            "lat": -17.77755,
            "lng": -63.211717
        },
        {
            "lat": -17.77755,
            "lng": -63.212233
        },
        {
            "lat": -17.777567,
            "lng": -63.21275
        },
        {
            "lat": -17.777617,
            "lng": -63.213267
        },
        {
            "lat": -17.777633,
            "lng": -63.213767
        },
        {
            "lat": -17.777283,
            "lng": -63.213917
        },
        {
            "lat": -17.776833,
            "lng": -63.213817
        },
        {
            "lat": -17.7765,
            "lng": -63.213517
        },
        {
            "lat": -17.7761,
            "lng": -63.213183
        },
        {
            "lat": -17.775683,
            "lng": -63.212817
        },
        {
            "lat": -17.775317,
            "lng": -63.2125
        },
        {
            "lat": -17.774917,
            "lng": -63.21215
        },
        {
            "lat": -17.774533,
            "lng": -63.211833
        },
        {
            "lat": -17.7741,
            "lng": -63.211467
        },
        {
            "lat": -17.773667,
            "lng": -63.2111
        },
        {
            "lat": -17.7733,
            "lng": -63.210783
        },
        {
            "lat": -17.772933,
            "lng": -63.210467
        },
        {
            "lat": -17.772533,
            "lng": -63.210133
        },
        {
            "lat": -17.77215,
            "lng": -63.209817
        },
        {
            "lat": -17.7718,
            "lng": -63.209467
        },
        {
            "lat": -17.771483,
            "lng": -63.2091
        },
        {
            "lat": -17.771517,
            "lng": -63.208583
        },
        {
            "lat": -17.771583,
            "lng": -63.208017
        },
        {
            "lat": -17.7716,
            "lng": -63.207567
        },
        {
            "lat": -17.7711,
            "lng": -63.207383
        },
        {
            "lat": -17.770667,
            "lng": -63.207167
        },
        {
            "lat": -17.770217,
            "lng": -63.20695
        },
        {
            "lat": -17.769717,
            "lng": -63.2067
        },
        {
            "lat": -17.769267,
            "lng": -63.206467
        },
        {
            "lat": -17.7688,
            "lng": -63.2062
        },
        {
            "lat": -17.768817,
            "lng": -63.205783
        },
        {
            "lat": -17.769017,
            "lng": -63.205317
        },
        {
            "lat": -17.769267,
            "lng": -63.204817
        },
        {
            "lat": -17.769467,
            "lng": -63.204367
        },
        {
            "lat": -17.769083,
            "lng": -63.204067
        },
        {
            "lat": -17.76865,
            "lng": -63.20385
        }
    ],
    "distance": "24.4000",
    "id": 109
}